hi_minju210/__init__.py
hi_minju210/hello.py
hi_minju210-0.8.0.dist-info/METADATA
hi_minju210-0.8.0.dist-info/WHEEL
hi_minju210-0.8.0.dist-info/entry_points.txt
hi_minju210-0.8.0.dist-info/top_level.txt
hi_minju210-0.8.0.dist-info/RECORD
