Metadata-Version: 2.1
Name: hi_minju210
Version: 0.8.0
Summary: Default template for PDM package
Author-email: minju210 <juliana6190210@gmail.com>
License: MIT
Requires-Python: ==3.12.*
